{
  "_fv": 13,
  "_type": "recipe",
  "definition": {
    "recipeType": "Crafting",
    "xpReward": 0.0,
    "cookingTime": 200,
    "recipeRetstackSize": 1,
    "group": "",
    "recipeShapeless": false,
    "recipeSlots": [
      {
        "value": ""
      },
      {
        "value": "Items.SUGAR"
      },
      {
        "value": ""
      },
      {
        "value": "Items.DYE#3"
      },
      {
        "value": "CUSTOM:RootBeerCan"
      },
      {
        "value": "Items.POTIONITEM"
      },
      {
        "value": ""
      },
      {
        "value": ""
      },
      {
        "value": ""
      }
    ],
    "recipeReturnStack": {
      "value": "CUSTOM:RootBeer"
    },
    "name": "root_beer_recipe",
    "namespace": "mod"
  }
}